swatcher/__init__.py
swatcher/color.py
swatcher/export.py
swatcher/image.py
swatcher/palette.py
swatcher-1.0.3.dist-info/LICENSE
swatcher-1.0.3.dist-info/METADATA
swatcher-1.0.3.dist-info/WHEEL
swatcher-1.0.3.dist-info/top_level.txt
swatcher-1.0.3.dist-info/RECORD
