Metadata-Version: 2.1
Name: swatcher
Version: 1.0.3
Summary: Generate Adobe ASE swatches from images.
Home-page: http://github.com/joshbduncan/swatcher
Author: Josh Duncan
Author-email: joshbduncan@gmail.com
License: MIT
Keywords: adobe,color,swatches
Platform: UNKNOWN
Classifier: Programming Language :: Python :: 3
Classifier: License :: OSI Approved :: MIT License
Classifier: Operating System :: OS Independent
Requires-Python: >=3.8
License-File: LICENSE
Requires-Dist: Pillow
